clickarrow-0.1.0.dist-info/METADATA
clickarrow-0.1.0.dist-info/WHEEL
clickhouse_arrow.libs/libgcc_s-6d2d9dc8.so.1
clickhouse_arrow/_internal.pyi
clickhouse_arrow/__init__.py
clickhouse_arrow/_internal.abi3.so
clickarrow-0.1.0.dist-info/RECORD
