Metadata-Version: 2.4
Name: clickarrow
Version: 0.1.0
Classifier: Development Status :: 4 - Beta
Classifier: Programming Language :: Rust
Classifier: Programming Language :: Python :: Implementation :: CPython
Classifier: Programming Language :: Python :: 3.9
Classifier: Programming Language :: Python :: 3.10
Classifier: Programming Language :: Python :: 3.11
Classifier: Programming Language :: Python :: 3.12
Classifier: Programming Language :: Python :: 3.13
Classifier: License :: OSI Approved :: Apache Software License
Classifier: Topic :: Database
Requires-Dist: pyarrow>=14.0.0
Summary: High-performance ClickHouse client with native protocol and Arrow integration
Keywords: clickhouse,arrow,database,analytics
Home-Page: https://github.com/georgeleepatterson/clickhouse-arrow
License: Apache-2.0
Requires-Python: >=3.9
Project-URL: Homepage, https://github.com/georgeleepatterson/clickhouse-arrow
Project-URL: Repository, https://github.com/georgeleepatterson/clickhouse-arrow
Project-URL: Documentation, https://docs.rs/clickhouse-arrow
